ao3downloader/__init__.py
ao3downloader/ao3.py
ao3downloader/exceptions.py
ao3downloader/fileio.py
ao3downloader/main.py
ao3downloader/parse_pdf.py
ao3downloader/parse_soup.py
ao3downloader/parse_text.py
ao3downloader/parse_xml.py
ao3downloader/repo.py
ao3downloader/strings.py
ao3downloader/update.py
ao3downloader/actions/__init__.py
ao3downloader/actions/ao3download.py
ao3downloader/actions/enterlinks.py
ao3downloader/actions/getlinks.py
ao3downloader/actions/ignorelist.py
ao3downloader/actions/logvisualization.py
ao3downloader/actions/markedforlater.py
ao3downloader/actions/pinboarddownload.py
ao3downloader/actions/redownload.py
ao3downloader/actions/shared.py
ao3downloader/actions/updatefics.py
ao3downloader/actions/updateseries.py
ao3downloader/html/template.html
ao3downloader/settings/settings.ini
ao3downloader-2025.6.1.dist-info/METADATA
ao3downloader-2025.6.1.dist-info/WHEEL
ao3downloader-2025.6.1.dist-info/entry_points.txt
ao3downloader-2025.6.1.dist-info/licenses/LICENSE
ao3downloader-2025.6.1.dist-info/RECORD
