Metadata-Version: 2.4
Name: ao3downloader
Version: 2025.6.1
Summary: Utility for downloading fanfiction in bulk from the Archive of Our Own
Project-URL: Homepage, https://nianeyna.dev/ao3downloader
Project-URL: Repository, https://github.com/nianeyna/ao3downloader
Author-email: nianeyna <nianeyna@gmail.com>
License-Expression: GPL-3.0-only
License-File: LICENSE
Keywords: ao3,ao3 downloader,archive of our own,bulk download,downloader,fanfiction
Requires-Python: <3.13,>=3.9
Requires-Dist: beautifulsoup4>=4.13.4
Requires-Dist: mobi>=0.3.3
Requires-Dist: pdfquery>=0.4.3
Requires-Dist: requests>=2.32.4
Requires-Dist: six>=1.17.0
Requires-Dist: tqdm>=4.67.1
